README.md
setup.py
debug_hemin/__init__.py
debug_hemin/print_str.py
debug_hemin.egg-info/PKG-INFO
debug_hemin.egg-info/SOURCES.txt
debug_hemin.egg-info/dependency_links.txt
debug_hemin.egg-info/top_level.txt