Metadata-Version: 2.1
Name: debug-hemin
Version: 0.0.2
Summary: PyPI Tutorial
Home-page: https://github.com
Author: hemin
Author-email: hemin@aiotek.pro
License: UNKNOWN
Platform: UNKNOWN
Classifier: Programming Language :: Python :: 3
Classifier: License :: OSI Approved :: MIT License
Classifier: Operating System :: OS Independent
